Ramlal_STT/__init__.py
ramlal_stt-0.1.dist-info/METADATA
ramlal_stt-0.1.dist-info/WHEEL
ramlal_stt-0.1.dist-info/top_level.txt
ramlal_stt-0.1.dist-info/RECORD
