Metadata-Version: 2.4
Name: Ramlal_STT
Version: 0.1
Summary: This is speech to text package for Ramlal.
Author: Ramlal
Author-email: ramlal@gmail.com
Dynamic: author
Dynamic: author-email
Dynamic: summary
